hn_test_sum/__init__.py
hn_test_sum/sum_num.py
hn_test_sum-0.0.1.dist-info/LICENSE.txt
hn_test_sum-0.0.1.dist-info/METADATA
hn_test_sum-0.0.1.dist-info/WHEEL
hn_test_sum-0.0.1.dist-info/entry_points.txt
hn_test_sum-0.0.1.dist-info/top_level.txt
hn_test_sum-0.0.1.dist-info/RECORD
